{
  "11_12_2024": {
    "xFollows": 40,
    "bskyFollows": 77
  },
  "11_13_2024": {
    "xFollows": 46,
    "bskyFollows": 92
  },
  "11_14_2024": {
    "xFollows": 46,
    "bskyFollows": 96
  },
  "11_15_2024": {
    "xFollows": 52,
    "bskyFollows": 105
  },
  "11_16_2024": {
    "xFollows": 54,
    "bskyFollows": 111
  },
  "11_17_2024": {
    "xFollows": 54,
    "bskyFollows": 117
  },
  "11_18_2024": {
    "xFollows": 54,
    "bskyFollows": 117
  },
  "11_19_2024": {
    "xFollows": 56,
    "bskyFollows": 124
  },
  "11_20_2024": {
    "xFollows": 57,
    "bskyFollows": 142
  },
  "11_21_2024": {
    "xFollows": 59,
    "bskyFollows": 161
  },
  "11_22_2024": {
    "xFollows": 60,
    "bskyFollows": 174
  }
}